{
  "purchases" : [
  {
    "product": "in id exercitation",
    "price": "$182.31",
    "date": "Aug Sa, 2019",
    "state": 2
  },
  {
    "product": "sit dolor officia",
    "price": "$123.59",
    "date": "Dec Th, 2018",
    "state": 3
  },
  {
    "product": "elit incididunt nostrud",
    "price": "$101.27",
    "date": "Jan Sa, 2016",
    "state": 2
  },
  {
    "product": "excepteur nostrud id",
    "price": "$262.38",
    "date": "Sep We, 2017",
    "state": 2
  },
  {
    "product": "aliqua et deserunt",
    "price": "$300.87",
    "date": "May Sa, 2015",
    "state": 1
  },
  {
    "product": "magna eiusmod sint",
    "price": "$354.88",
    "date": "Aug Mo, 2015",
    "state": 1
  },
  {
    "product": "ex est elit",
    "price": "$145.03",
    "date": "Apr We, 2015",
    "state": 2
  },
  {
    "product": "voluptate dolore et",
    "price": "$294.02",
    "date": "Aug Sa, 2014",
    "state": 3
  },
  {
    "product": "exercitation nostrud quis",
    "price": "$119.78",
    "date": "Nov Mo, 2017",
    "state": 1
  },
  {
    "product": "Lorem incididunt amet",
    "price": "$305.33",
    "date": "Sep Sa, 2017",
    "state": 2
  },
  {
    "product": "laboris id nisi",
    "price": "$170.79",
    "date": "Mar Sa, 2019",
    "state": 1
  },
  {
    "product": "sint mollit eiusmod",
    "price": "$219.74",
    "date": "May Th, 2018",
    "state": 1
  },
  {
    "product": "ea excepteur id",
    "price": "$275.44",
    "date": "Feb Tu, 2015",
    "state": 1
  },
  {
    "product": "incididunt non consectetur",
    "price": "$252.65",
    "date": "Oct Tu, 2019",
    "state": 3
  },
  {
    "product": "nulla anim enim",
    "price": "$160.88",
    "date": "Aug Mo, 2014",
    "state": 3
  },
  {
    "product": "Lorem aliquip consectetur",
    "price": "$168.01",
    "date": "Dec Fr, 2015",
    "state": 3
  },
  {
    "product": "quis est voluptate",
    "price": "$319.44",
    "date": "Jan Su, 2016",
    "state": 2
  },
  {
    "product": "elit enim veniam",
    "price": "$320.91",
    "date": "Feb Fr, 2018",
    "state": 2
  },
  {
    "product": "quis quis eiusmod",
    "price": "$375.59",
    "date": "Mar Mo, 2018",
    "state": 3
  },
  {
    "product": "nisi ea fugiat",
    "price": "$153.14",
    "date": "Jun Th, 2014",
    "state": 3
  },
  {
    "product": "adipisicing pariatur aute",
    "price": "$332.51",
    "date": "May Fr, 2016",
    "state": 3
  },
  {
    "product": "veniam commodo nostrud",
    "price": "$387.27",
    "date": "Jul Th, 2019",
    "state": 1
  },
  {
    "product": "anim excepteur fugiat",
    "price": "$255.88",
    "date": "Feb Su, 2018",
    "state": 1
  },
  {
    "product": "minim do est",
    "price": "$237.13",
    "date": "Feb Su, 2017",
    "state": 3
  },
  {
    "product": "est exercitation laborum",
    "price": "$228.73",
    "date": "May Fr, 2015",
    "state": 3
  },
  {
    "product": "Lorem ut et",
    "price": "$164.78",
    "date": "Mar Tu, 2017",
    "state": 1
  },
  {
    "product": "ut in quis",
    "price": "$106.98",
    "date": "Sep Sa, 2014",
    "state": 1
  },
  {
    "product": "veniam sunt exercitation",
    "price": "$217.26",
    "date": "Oct Sa, 2018",
    "state": 3
  },
  {
    "product": "ea non dolor",
    "price": "$112.11",
    "date": "Mar Fr, 2018",
    "state": 2
  },
  {
    "product": "commodo nostrud ut",
    "price": "$116.84",
    "date": "Dec We, 2015",
    "state": 1
  },
  {
    "product": "culpa eu exercitation",
    "price": "$325.11",
    "date": "Apr Mo, 2015",
    "state": 3
  },
  {
    "product": "magna cillum non",
    "price": "$363.45",
    "date": "Apr Sa, 2017",
    "state": 3
  },
  {
    "product": "Lorem sunt duis",
    "price": "$101.75",
    "date": "May Th, 2015",
    "state": 3
  },
  {
    "product": "labore culpa excepteur",
    "price": "$316.28",
    "date": "Apr Su, 2017",
    "state": 3
  },
  {
    "product": "nostrud laborum esse",
    "price": "$301.32",
    "date": "Mar Th, 2014",
    "state": 3
  },
  {
    "product": "commodo culpa ex",
    "price": "$258.60",
    "date": "Aug Tu, 2015",
    "state": 3
  },
  {
    "product": "ut officia proident",
    "price": "$393.42",
    "date": "May Mo, 2015",
    "state": 2
  },
  {
    "product": "fugiat laborum fugiat",
    "price": "$313.82",
    "date": "Mar Sa, 2019",
    "state": 3
  },
  {
    "product": "est et voluptate",
    "price": "$146.09",
    "date": "Jun We, 2019",
    "state": 2
  },
  {
    "product": "in dolor cupidatat",
    "price": "$146.39",
    "date": "May Fr, 2014",
    "state": 1
  },
  {
    "product": "consequat excepteur dolor",
    "price": "$390.56",
    "date": "Jul Th, 2019",
    "state": 1
  },
  {
    "product": "officia nostrud id",
    "price": "$119.56",
    "date": "Jul We, 2019",
    "state": 2
  },
  {
    "product": "adipisicing ad proident",
    "price": "$289.91",
    "date": "Aug We, 2014",
    "state": 3
  },
  {
    "product": "consectetur excepteur nulla",
    "price": "$298.79",
    "date": "Apr Tu, 2017",
    "state": 2
  },
  {
    "product": "Lorem ex sit",
    "price": "$267.39",
    "date": "Aug Mo, 2015",
    "state": 1
  },
  {
    "product": "in deserunt id",
    "price": "$131.40",
    "date": "Dec Mo, 2017",
    "state": 2
  },
  {
    "product": "nostrud consectetur pariatur",
    "price": "$156.31",
    "date": "Dec Tu, 2015",
    "state": 2
  },
  {
    "product": "anim velit occaecat",
    "price": "$218.86",
    "date": "Jun Mo, 2018",
    "state": 3
  },
  {
    "product": "mollit in cillum",
    "price": "$142.25",
    "date": "Aug Sa, 2016",
    "state": 3
  },
  {
    "product": "ipsum nulla fugiat",
    "price": "$297.60",
    "date": "Jul Mo, 2015",
    "state": 2
  },
  {
    "product": "amet amet fugiat",
    "price": "$375.38",
    "date": "Dec We, 2014",
    "state": 3
  },
  {
    "product": "amet do commodo",
    "price": "$284.36",
    "date": "Nov Mo, 2015",
    "state": 2
  },
  {
    "product": "fugiat labore ullamco",
    "price": "$191.65",
    "date": "Apr Su, 2017",
    "state": 3
  },
  {
    "product": "anim voluptate aliqua",
    "price": "$152.95",
    "date": "Aug Sa, 2016",
    "state": 3
  },
  {
    "product": "laborum aute et",
    "price": "$293.04",
    "date": "Apr Sa, 2016",
    "state": 2
  },
  {
    "product": "deserunt ea fugiat",
    "price": "$193.46",
    "date": "Sep We, 2017",
    "state": 2
  },
  {
    "product": "ea sint dolore",
    "price": "$302.00",
    "date": "Aug Tu, 2019",
    "state": 2
  },
  {
    "product": "voluptate elit quis",
    "price": "$300.69",
    "date": "May Th, 2018",
    "state": 1
  },
  {
    "product": "mollit do anim",
    "price": "$110.83",
    "date": "Apr Th, 2019",
    "state": 1
  },
  {
    "product": "enim nisi deserunt",
    "price": "$117.43",
    "date": "Dec Mo, 2018",
    "state": 1
  },
  {
    "product": "cillum voluptate duis",
    "price": "$316.38",
    "date": "Jul We, 2015",
    "state": 2
  },
  {
    "product": "excepteur pariatur sunt",
    "price": "$143.52",
    "date": "Mar Sa, 2015",
    "state": 2
  },
  {
    "product": "elit sunt cillum",
    "price": "$204.22",
    "date": "May Mo, 2019",
    "state": 1
  },
  {
    "product": "ea reprehenderit non",
    "price": "$158.15",
    "date": "Aug Fr, 2014",
    "state": 2
  },
  {
    "product": "eu qui reprehenderit",
    "price": "$263.87",
    "date": "Sep Tu, 2019",
    "state": 3
  },
  {
    "product": "occaecat ea pariatur",
    "price": "$219.53",
    "date": "Jul Th, 2018",
    "state": 1
  },
  {
    "product": "officia mollit excepteur",
    "price": "$140.80",
    "date": "May Fr, 2015",
    "state": 3
  },
  {
    "product": "eu cupidatat in",
    "price": "$304.27",
    "date": "Apr Sa, 2014",
    "state": 3
  },
  {
    "product": "dolore reprehenderit nostrud",
    "price": "$214.86",
    "date": "Dec We, 2017",
    "state": 3
  },
  {
    "product": "magna qui culpa",
    "price": "$340.49",
    "date": "Mar We, 2014",
    "state": 3
  },
  {
    "product": "sint commodo ut",
    "price": "$370.62",
    "date": "Oct Mo, 2018",
    "state": 1
  },
  {
    "product": "aliqua minim culpa",
    "price": "$322.33",
    "date": "May Fr, 2017",
    "state": 3
  },
  {
    "product": "dolore consectetur ipsum",
    "price": "$132.57",
    "date": "Jan Mo, 2016",
    "state": 2
  },
  {
    "product": "anim duis qui",
    "price": "$135.12",
    "date": "Sep Fr, 2019",
    "state": 2
  },
  {
    "product": "labore aute velit",
    "price": "$218.50",
    "date": "Feb Th, 2018",
    "state": 3
  },
  {
    "product": "duis occaecat tempor",
    "price": "$160.33",
    "date": "Jul Mo, 2019",
    "state": 3
  },
  {
    "product": "ea adipisicing reprehenderit",
    "price": "$224.99",
    "date": "May Th, 2017",
    "state": 2
  },
  {
    "product": "sit consequat ad",
    "price": "$352.07",
    "date": "Nov Mo, 2018",
    "state": 3
  }
]
}
